poetry_drill_demo/__init__.py
poetry_drill_demo/main.py
poetry_drill_demo-0.1.0.dist-info/METADATA
poetry_drill_demo-0.1.0.dist-info/WHEEL
poetry_drill_demo-0.1.0.dist-info/entry_points.txt
poetry_drill_demo-0.1.0.dist-info/RECORD
