Metadata-Version: 2.1
Name: poetry-drill-demo
Version: 0.1.0
Summary: 
Author: stevepurpose
Author-email: stevenpurpose@gmail.com
Requires-Python: >=3.8,<4.0
Classifier: Programming Language :: Python :: 3
Classifier: Programming Language :: Python :: 3.8
Classifier: Programming Language :: Python :: 3.9
Classifier: Programming Language :: Python :: 3.10
Classifier: Programming Language :: Python :: 3.11
Classifier: Programming Language :: Python :: 3.12
Classifier: Programming Language :: Python :: 3.13
Requires-Dist: typer (>=0.14.0,<0.15.0)
